pyprivacy/__init__.py
pyprivacy/context_building.py
pyprivacy/core.py
pyprivacy/user_secrets.py
pyprivacy/decorators/__init__.py
pyprivacy/decorators/base_decorator.py
pyprivacy/decorators/external_decorator.py
pyprivacy/decorators/transform_decorator.py
pyprivacy/decorators/use_decorator.py
pyprivacy/decorators/advanced/__init__.py
pyprivacy/decorators/advanced/comparison_decorator.py
pyprivacy/primitives/__init__.py
pyprivacy/primitives/collection.py
pyprivacy/primitives/data.py
pyprivacy/primitives/data_policy_pair.py
pyprivacy/primitives/policy.py
pyprivacy/primitives/result.py
pyprivacy/primitives/policy_helpers/__init__.py
pyprivacy/primitives/policy_helpers/policy_lexer.py
pyprivacy/primitives/policy_helpers/policy_parser.py
pyprivacy/primitives/policy_helpers/private_data.py
pyprivacy/primitives/policy_helpers/expressions/__init__.py
pyprivacy/primitives/policy_helpers/expressions/base_expression.py
pyprivacy/primitives/policy_helpers/expressions/binary/__init__.py
pyprivacy/primitives/policy_helpers/expressions/binary/binary_expression.py
pyprivacy/primitives/policy_helpers/expressions/binary/concat_expression.py
pyprivacy/primitives/policy_helpers/expressions/binary/intersect_expression.py
pyprivacy/primitives/policy_helpers/expressions/binary/union_expression.py
pyprivacy/primitives/policy_helpers/expressions/special/__init__.py
pyprivacy/primitives/policy_helpers/expressions/special/action_expression.py
pyprivacy/primitives/policy_helpers/expressions/special/assign_expression.py
pyprivacy/primitives/policy_helpers/expressions/special/command.py
pyprivacy/primitives/policy_helpers/expressions/special/constant_expression.py
pyprivacy/primitives/policy_helpers/expressions/special/constants.py
pyprivacy/primitives/policy_helpers/expressions/special/test_expression.py
pyprivacy/primitives/policy_helpers/expressions/special/tests.py
pyprivacy/primitives/policy_helpers/expressions/unary/__init__.py
PyPrivacy-0.0.1.dist-info/LICENSE
PyPrivacy-0.0.1.dist-info/METADATA
PyPrivacy-0.0.1.dist-info/WHEEL
PyPrivacy-0.0.1.dist-info/top_level.txt
PyPrivacy-0.0.1.dist-info/RECORD
